setup.py
gaeforms/__init__.py
gaeforms/base.py
gaeforms/settings.py
gaeforms.egg-info/PKG-INFO
gaeforms.egg-info/SOURCES.txt
gaeforms.egg-info/dependency_links.txt
gaeforms.egg-info/not-zip-safe
gaeforms.egg-info/requires.txt
gaeforms.egg-info/top_level.txt
gaeforms/country/__init__.py
gaeforms/country/br/__init__.py
gaeforms/country/br/field.py
gaeforms/country/br/property.py
gaeforms/ndb/__init__.py
gaeforms/ndb/form.py
gaeforms/ndb/property.py